.gitignore
LICENSE.txt
README.rst
increment_version.py
requirements.txt
setup.cfg
setup.py
friendlyfred/__init__.py
friendlyfred/categories.py
friendlyfred/friendlyfred.py
friendlyfred/utils.py
friendlyfred/version.py
friendlyfred.egg-info/PKG-INFO
friendlyfred.egg-info/SOURCES.txt
friendlyfred.egg-info/dependency_links.txt
friendlyfred.egg-info/requires.txt
friendlyfred.egg-info/top_level.txt
img/observations.png
img/tree_depth_0.png
img/tree_depth_2.png
img/tree_series.png