Metadata-Version: 2.1
Name: friendlyfred
Version: 0.1.2
Summary: FRED data API wrapper for Python
Home-page: https://github.com/DanilZherebtsov/friendlyfred
Download-URL: https://github.com/DanilZherebtsov/friendlyfred/archive/refs/tags/0.1.2.tar.gz
Author: Danil Zherebtsov
Author-email: danil.com@me.com
License: MIT
Keywords: fred,economics,macroeconomic,data
Classifier: Development Status :: 4 - Beta
Classifier: Intended Audience :: Developers
Classifier: Topic :: Software Development :: Build Tools
Classifier: License :: OSI Approved :: MIT License
Classifier: Programming Language :: Python :: 3.7
Classifier: Programming Language :: Python :: 3.8
Classifier: Programming Language :: Python :: 3.9
Classifier: Programming Language :: Python :: 3.10
Classifier: Programming Language :: Python :: 3.11
License-File: LICENSE.txt
